simulai/__init__.py
simulai/interface.py
simulai/sim.py
simulai-0.0.1.dist-info/LICENSE
simulai-0.0.1.dist-info/METADATA
simulai-0.0.1.dist-info/WHEEL
simulai-0.0.1.dist-info/top_level.txt
simulai-0.0.1.dist-info/RECORD
