Metadata-Version: 2.1
Name: simulai
Version: 0.0.1
Summary: SimulAI - Simulation + Artificial Intelligence
Home-page: https://github.com/carosaav/SimulAI
Author: ['Perez Colo Ivo', 'Pirozzo Manuel Bernardo', 'Saavedra Sueldo Carolina']
Author-email: ivoperezcolo@gmail.com
License: MIT
Keywords: simulai,simulation,artificial intelligence,decision sciences,optimization
Platform: UNKNOWN
Classifier: Development Status :: 4 - Beta
Classifier: Intended Audience :: Education
Classifier: Intended Audience :: Science/Research
Classifier: License :: OSI Approved :: MIT License
Classifier: Operating System :: Microsoft :: Windows
Classifier: Programming Language :: Python
Classifier: Programming Language :: Python :: 3.8
Classifier: Topic :: Scientific/Engineering
Requires-Dist: numpy
Requires-Dist: attrs
Requires-Dist: pywin32
